smallstep/README.md
smallstep/__init__.py
smallstep/api.py
smallstep/api_client/__init__.py
smallstep/api_client/api/__init__.py
smallstep/api_client/api/attestation/__init__.py
smallstep/api_client/api/attestation/delete_attestation_authority.py
smallstep/api_client/api/attestation/get_attestation_authorities.py
smallstep/api_client/api/attestation/get_attestation_authority.py
smallstep/api_client/api/attestation/post_attestation_authorities.py
smallstep/api_client/api/authenticate/__init__.py
smallstep/api_client/api/authenticate/post_auth.py
smallstep/api_client/api/authorities/__init__.py
smallstep/api_client/api/authorities/delete_authority.py
smallstep/api_client/api/authorities/get_authorities.py
smallstep/api_client/api/authorities/get_authority.py
smallstep/api_client/api/authorities/post_authorities.py
smallstep/api_client/api/authorities/post_authorities_csr.py
smallstep/api_client/api/authorities/post_authority_root.py
smallstep/api_client/api/collections/__init__.py
smallstep/api_client/api/collections/delete_collection.py
smallstep/api_client/api/collections/delete_collection_instance.py
smallstep/api_client/api/collections/get_collection.py
smallstep/api_client/api/collections/get_collection_instance.py
smallstep/api_client/api/collections/get_collection_instance_data.py
smallstep/api_client/api/collections/list_collection_instances.py
smallstep/api_client/api/collections/list_collections.py
smallstep/api_client/api/collections/post_collections.py
smallstep/api_client/api/collections/put_collection.py
smallstep/api_client/api/collections/put_collection_instance.py
smallstep/api_client/api/collections/put_collection_instance_data.py
smallstep/api_client/api/managed_workloads/__init__.py
smallstep/api_client/api/managed_workloads/delete_agent_configuration.py
smallstep/api_client/api/managed_workloads/delete_device_collection.py
smallstep/api_client/api/managed_workloads/delete_endpoint_configuration.py
smallstep_python-0.1.1.dist-info/LICENSE
smallstep_python-0.1.1.dist-info/METADATA
smallstep_python-0.1.1.dist-info/WHEEL
smallstep_python-0.1.1.dist-info/RECORD
