Metadata-Version: 2.1
Name: smallstep-python
Version: 0.1.1
Summary: A Python library at allows you to interface with the Smallstep API.
Home-page: https://github.com/smallstep/smallstep-python
Author: Smallstep Engineering
Author-email: techadmin@smallstep.com
Requires-Python: >=3.9,<4.0
Classifier: Programming Language :: Python :: 3
Classifier: Programming Language :: Python :: 3.9
Classifier: Programming Language :: Python :: 3.10
Classifier: Programming Language :: Python :: 3.11
Requires-Dist: openapi-python-client (==0.15.2)
Requires-Dist: pydantic-settings (==2.0.3)
Requires-Dist: pyhumps (>=3.8.0,<4.0.0)
Project-URL: Repository, https://github.com/smallstep/smallstep-python
